Workbook

Sheet Lisez-moi
B2: PROJET HERMÈS — MODÈLE DE CARVE-OUT
B3: Reconstruction pédagogique de l'opération Opella (Sanofi / CD&R, closing 30 avril 2025)
B5: Objet | C5: Modéliser la mécanique financière d'un carve-out : du P&L « périmètre » publié par le vendeur vers un EBITDA stand-alone pro forma, en passant par la réintégration des allocations groupe, les coûts stand-alone récurrents, la TSA (Transition Services Agreement) et les coûts de séparation one-off.
B6: Cas d'ancrage | C6: Opella (santé grand public de Sanofi) : EV ≈ 16 Md€, ≈ 14x l'EBITDA 2024e, CD&R 50,0 % / Sanofi 48,2 % / Bpifrance 1,8 %, closing 30/04/2025. Chiffres d'ancrage publics ; ajustements carve-out = hypothèses illustratives du rédacteur (« e »).
B7: Structure | C7: Onglet Hypothèses (toutes les entrées en bleu) → P&L Carve-out (mécanique périmètre → stand-alone → pro forma) → TSA (échéancier des services transitoires) → Valo & Retours (structure d'equity et retours CD&R illustratifs).
B8: Convention de calendrier | C8: Le closing est intervenu le 30/04/2025 mais le modèle raisonne en années civiles pleines (2025E = 12 mois) : simplification assumée et documentée. Les coûts de TSA et one-off 2025 sont donc légèrement surestimés (12 mois au lieu de 8 post-closing) — conservateur. Une vraie année 1 glissante (mai 2025 - avril 2026) serait la convention contractuelle exacte.
B9: Code couleur | C9: Bleu : inputs modifiables. Noir : formules. Vert : liens inter-onglets. Fond jaune : hypothèses structurantes à challenger.
B10: Sources | C10: Communiqués Sanofi des 21/10/2024 et 30/04/2025 ; presse financière (Transacted, FiercePharma). Aucune donnée non publique.
B11: Avertissement | C11: Document de démonstration méthodologique préparé par Hamza Ben Chaouch (ESSEC) pour un dossier de candidature. Ne constitue ni un conseil ni une valorisation d'Opella.
B13: REGISTRE DES SOURCES
B14: S1 | C14: Communiqué de presse Sanofi — négociations exclusives avec CD&R sur Opella : EV c.16 Md€, c.14x EBITDA 2024e. Ce sont les deux seuls chiffres publiés — le communiqué ne donne pas de chiffre d'affaires. Date : 21/10/2024. Canal : sanofi.com (espace presse). Alimente : Hypothèses!C8 (EV 16 000 M€) et l'ancrage du multiple d'entrée. Le CA de ~5,0 Md€ (C5) est un ordre de grandeur presse/analystes classé estimation ; la marge (C6) est un résidu calculé des deux ancrages, pas une donnée publiée.
B15: S2 | C15: Communiqué de presse Sanofi — closing de la cession d'Opella : répartition CD&R 50,0 % / Sanofi 48,2 % / Bpifrance 1,8 %. Date : 30/04/2025. Canal : sanofi.com (espace presse). Alimente : Hypothèses!C10:C12 (participations), convention de calendrier (Lisez-moi).
B16: S3 | C16: Presse financière (Transacted, FiercePharma) — recoupement de l'EV et du multiple d'entrée. Dates : oct. 2024 - avr. 2025. Canal : en ligne. Alimente : recoupement de S1, aucune cellule propre.
B17: S4 | C17: Estimations du rédacteur (« e ») — CA périmètre, trajectoire opérationnelle, ajustements de carve-out, TSA, financement et sortie. Dates : construites le 08/07/2026, revues le 16/07/2026 (CA 5,0 Md€, coût de dette câblé). Alimente : Hypothèses!C5 (avec S1 pour les ancrages), C15:C16, C19:C23, C27, C29:C30, C33:C36 et TSA!C5:D9 — C24 et C28 sont des formules et les lignes intercalaires des titres ou des vides, pas des inputs. Chaque hypothèse porte sa justification en colonne D de l'onglet Hypothèses.

Sheet Hypothèses
B2: HYPOTHÈSES
B4: Périmètre et transaction
B5: Chiffre d'affaires périmètre FY2024 (M€) | C5: 5000 | D5: Ordre de grandeur public ~5,0 Md€ (réconcilié le 16/07/2026 — l'ancien 5,2 n'était pas soutenu par la source). Ancrages durs du deal : EV 16 Md€ et ~14x EBITDA 2024e (Sanofi, 21/10/2024)
B6: Marge d'EBITDA périmètre FY2024 (avant ajustements) | C6: 0.2286 | D6: Résidu des deux ancrages publiés : EV 16 Md€ / 14x = EBITDA ≈ 1 143 M€, soit ≈ 22,9 % d'un CA de ~5,0 Md€ — la marge n'est pas publiée, elle est implicite du deal
B7: EBITDA périmètre FY2024 (M€) | C7: =C5*C6 -> 1143
B8: Valeur d'entreprise de la transaction (M€) | C8: 16000 | D8: Source : communiqué Sanofi 21/10/2024 — EV c.16 Md€, c.14x EBITDA 2024e
B9: Multiple d'entrée implicite EV/EBITDA | C9: =C8/C7 -> 13.99825
B10: Participation CD&R | C10: 0.5 | D10: Communiqué closing 30/04/2025
B11: Participation Sanofi (conservée) | C11: 0.482 | D11: Communiqué closing 30/04/2025
B12: Participation Bpifrance | C12: 0.018 | D12: Communiqué closing 30/04/2025
B14: Trajectoire opérationnelle 2025-2029
B15: Croissance du CA (par an) | C15: 0.03 | D15: Hypothèse « e » : croissance CHC marché ~3-4 %
B16: Expansion de marge périmètre (pts/an) | C16: 0.003 | D16: Hypothèse « e » : mix et pricing
B18: Ajustements de carve-out (M€, en année pleine)
B19: Réintégration des allocations corporate du vendeur | C19: 80 | D19: Hypothèse « e » : coûts de siège alloués par Sanofi non repris tels quels (~1,5 % du CA)
B20: Coûts stand-alone — IT et infrastructure | C20: -40 | D20: Hypothèse « e » : ERP, licences, cybersécurité en propre
B21: Coûts stand-alone — fonctions support (finance, RH, juridique) | C21: -30 | D21: Hypothèse « e »
B22: Coûts stand-alone — distribution et achats (perte de mutualisation) | C22: -25 | D22: Hypothèse « e »
B23: Coûts stand-alone — qualité, réglementaire, pharmacovigilance | C23: -25 | D23: Hypothèse « e »
B24: Total coûts stand-alone récurrents | C24: =SUM(C20:C23) -> -120
B26: TSA et séparation
B27: Coût TSA année 1 (M€) | C27: -60 | D27: Hypothèse « e » : services facturés par Sanofi pendant la transition
B28: Coût TSA année 2 (M€) — proratisé par service, voir onglet TSA | C28: =TSA!E10 -> -38.5
B29: Coûts one-off de séparation (M€, total) | C29: -150 | D29: Hypothèse « e » : projet de séparation IT, rebranding, juridique — étalés 2025-2026
B30: Quote-part des one-offs en 2025 | C30: 0.6 | D30: Hypothèse « e » : phasage majoritaire en année 1 (IT et juridique engagés dès le closing), solde en 2026
B32: Financement et sortie (vue CD&R illustrative)
B33: Levier à l'entrée (x EBITDA stand-alone PF) | C33: 4 | D33: Hypothèse « e » : financement large-cap
B34: Coût moyen de la dette | C34: 0.055 | D34: Hypothèse « e » — CÂBLÉ dans le proxy de désendettement depuis le 16/07/2026 : intérêts approximés sur la dette d'entrée (constants, conservateur), 5 années de détention
B35: Multiple de sortie EV/EBITDA (2029) | C35: 14 | D35: Hypothèse « e » : maintien du multiple d'entrée
B36: Conversion de l'EBITDA cash en flux avant intérêts | C36: 0.45 | D36: Hypothèse « e » : après impôts, capex et BFR mais AVANT intérêts (désormais modélisés séparément via C34) — proxy, pas un cash-flow complet

Sheet P&L Carve-out
B2: P&L CARVE-OUT — DU PÉRIMÈTRE AU STAND-ALONE PRO FORMA (M€)
C4: FY2024 PF | D4: 2025E | E4: 2026E | F4: 2027E | G4: 2028E | H4: 2029E
B5: Chiffre d'affaires | C5: =Hypothèses!C5 -> 5000 | D5: =C5*(1+Hypothèses!$C$15) -> 5150 | E5: =D5*(1+Hypothèses!$C$15) -> 5304.5 | F5: =E5*(1+Hypothèses!$C$15) -> 5463.635 | G5: =F5*(1+Hypothèses!$C$15) -> 5627.5441 | H5: =G5*(1+Hypothèses!$C$15) -> 5796.3704
B6: Croissance (%) | D6: =D5/C5-1 -> 0.03 | E6: =E5/D5-1 -> 0.03 | F6: =F5/E5-1 -> 0.03 | G6: =G5/F5-1 -> 0.03 | H6: =H5/G5-1 -> 0.03
B8: Marge d'EBITDA périmètre (avant ajustements) | C8: =Hypothèses!C6 -> 0.2286 | D8: =C8+Hypothèses!$C$16 -> 0.2316 | E8: =D8+Hypothèses!$C$16 -> 0.2346 | F8: =E8+Hypothèses!$C$16 -> 0.2376 | G8: =F8+Hypothèses!$C$16 -> 0.2406 | H8: =G8+Hypothèses!$C$16 -> 0.2436
B9: EBITDA périmètre (tel qu'alloué par le vendeur) | C9: =C5*C8 -> 1143 | D9: =D5*D8 -> 1192.74 | E9: =E5*E8 -> 1244.4357 | F9: =F5*F8 -> 1298.1597 | G9: =G5*G8 -> 1353.9871 | H9: =H5*H8 -> 1411.9958
B11: Réintégration des allocations corporate | C11: =Hypothèses!$C$19 -> 80 | D11: =Hypothèses!$C$19 -> 80 | E11: =Hypothèses!$C$19 -> 80 | F11: =Hypothèses!$C$19 -> 80 | G11: =Hypothèses!$C$19 -> 80 | H11: =Hypothèses!$C$19 -> 80
B12: Coûts stand-alone récurrents | C12: =Hypothèses!$C$24 -> -120 | D12: =Hypothèses!$C$24 -> -120 | E12: =Hypothèses!$C$24 -> -120 | F12: =Hypothèses!$C$24 -> -120 | G12: =Hypothèses!$C$24 -> -120 | H12: =Hypothèses!$C$24 -> -120
B13: EBITDA stand-alone (année pleine) | C13: =C9+C11+C12 -> 1103 | D13: =D9+D11+D12 -> 1152.74 | E13: =E9+E11+E12 -> 1204.4357 | F13: =F9+F11+F12 -> 1258.1597 | G13: =G9+G11+G12 -> 1313.9871 | H13: =H9+H11+H12 -> 1371.9958
B14: Marge stand-alone (%) | C14: =C13/C5 -> 0.2206 | D14: =D13/D5 -> 0.22383301 | E14: =E13/E5 -> 0.22705923 | F14: =F13/F5 -> 0.23027887 | G14: =G13/G5 -> 0.2334921 | H14: =H13/H5 -> 0.23669913
B16: Coûts de TSA (transitoires) | C16: 0 | D16: =Hypothèses!$C$27 -> -60 | E16: =Hypothèses!$C$28 -> -38.5 | F16: 0 | G16: 0 | H16: 0
B17: Coûts one-off de séparation | C17: 0 | D17: =Hypothèses!$C$29*Hypothèses!$C$30 -> -90 | E17: =Hypothèses!$C$29*(1-Hypothèses!$C$30) -> -60 | F17: 0 | G17: 0 | H17: 0
B18: EBITDA pro forma « cash » (après TSA et one-offs) | C18: =C13+C16+C17 -> 1103 | D18: =D13+D16+D17 -> 1002.74 | E18: =E13+E16+E17 -> 1105.9357 | F18: =F13+F16+F17 -> 1258.1597 | G18: =G13+G16+G17 -> 1313.9871 | H18: =H13+H16+H17 -> 1371.9958
B21: Lecture : l'EBITDA « année pleine » stand-alone (ligne 13) est l'agrégat de valorisation ; l'EBITDA « cash » (ligne 18) mesure la réalité des flux pendant la transition — l'écart 2025-2026 (TSA + one-offs) doit être financé et se retrouve dans le bridge de dette nette au closing.

Sheet TSA
B2: TSA — SERVICES TRANSITOIRES (ILLUSTRATIF)
B4: Service | C4: Coût annuel an 1 (M€) | D4: Durée (mois) | E4: Coût an 2 (M€, proratisé) | F4: Stratégie de sortie
B5: IT (ERP, infrastructure, support) | C5: -25 | D5: 24 | E5: =C5*MAX(0,MIN(12,D5-12))/12 -> -25 | G5: Migration vers un ERP en propre ; contrat d'infogérance
B6: Supply chain et logistique | C6: -15 | D6: 18 | E6: =C6*MAX(0,MIN(12,D6-12))/12 -> -7.5 | G6: Reprise des contrats 3PL en direct
B7: Finance (comptabilité, paie, fiscalité) | C7: -10 | D7: 12 | E7: =C7*MAX(0,MIN(12,D7-12))/12 -> 0 | G7: Internalisation + centre de services partagés
B8: Réglementaire et pharmacovigilance | C8: -6 | D8: 24 | E8: =C8*MAX(0,MIN(12,D8-12))/12 -> -6 | G8: Recrutement d'équipes dédiées (contrainte de licences)
B9: Autres (immobilier, achats) | C9: -4 | D9: 12 | E9: =C9*MAX(0,MIN(12,D9-12))/12 -> 0 | G9: Baux directs, contrats cadres propres
B10: Total TSA | C10: =SUM(C5:C9) -> -60 | E10: =SUM(E5:E9) -> -38.5
B12: Contrôle : le total an 1 doit être cohérent avec l'hypothèse globale (Hypothèses!C27). Année 2 : chaque service paie MAX(0; MIN(12; durée−12))/12 de son coût annuel — un service de 24 mois porte 12 mois pleins en année 2 (correction du forfait 50 % du 15/07/2026, audit §7.3).
B14: Écart contrôle an 1 (doit être 0) | C14: =C10-Hypothèses!C27 -> 0

Sheet Valo & Retours
B2: STRUCTURE ET RETOURS ILLUSTRATIFS (VUE CD&R)
B4: Structure à l'entrée (M€)
B5: Valeur d'entreprise | C5: =Hypothèses!C8 -> 16000
B6: EBITDA stand-alone FY2024 PF (référence) | C6: ='P&L Carve-out'!C13 -> 1103
B7: Multiple d'entrée sur stand-alone | C7: =C5/C6 -> 14.505893
B8: Dette d'acquisition (levier x EBITDA stand-alone) | C8: =Hypothèses!C33*C6 -> 4412
B9: Equity totale à l'entrée | C9: =C5-C8 -> 11588
B10: dont CD&R (50,0 %) | C10: =C9*Hypothèses!C10 -> 5794
B11: dont Sanofi (48,2 %) | C11: =C9*Hypothèses!C11 -> 5585.416
B12: dont Bpifrance (1,8 %) | C12: =C9*Hypothèses!C12 -> 208.584
B14: Sortie illustrative (2029)
B15: EBITDA stand-alone 2029E | C15: ='P&L Carve-out'!H13 -> 1371.9958
B16: Multiple de sortie | C16: =Hypothèses!C35 -> 14
B17: Valeur d'entreprise à la sortie | C17: =C15*C16 -> 19207.942
B18: Dette nette à la sortie (désendettement simplifié) | C18: =MAX(C8-(SUM('P&L Carve-out'!D18:H18)*Hypothèses!C36-5*Hypothèses!C34*C8),0) -> 2901.5318 | D18: Proxy : désendettement = conversion (C36) x EBITDA cash cumulé − 5 ans d'intérêts sur la dette d'entrée (C34 x C8, constants = conservateur). Toujours pas un debt schedule ni un cash-flow complet — mais le coût de dette agit désormais réellement sur le retour
B19: Equity à la sortie | C19: =C17-C18 -> 16306.41
B21: Retours CD&R (avant frais, dividendes exclus)
B22: MOIC | C22: =(C19*Hypothèses!C10)/C10 -> 1.4071807
B23: TRI (4,7 ans, closing avr. 2025 → 2029) | C23: =(C22)^(1/4.7)-1 -> 0.07538457
B25: Lecture assumée : le TRI illustratif ressort en single-digit (7,5 %) au prix payé — c'est une illustration mécanique, PAS un underwriting. L'entrée représente ~14,0x l'EBITDA périmètre publié implicite et ~14,5x l'EBITDA stand-alone après ajustements, contre 14,0x à la sortie. Le coût de dette consomme environ 1,65 point de TRI par rapport au proxy levered sans intérêts, mais le levier reste relutif face au cas non levered (~4,0 % non levered vs 7,5 % levered). À ce prix, le retour dépend d'abord de l'exécution : tenir les coûts stand-alone, sortir de la TSA à temps, expansion opérationnelle. La sensibilité clé reste la ligne des coûts stand-alone : +50 M€ récurrents = ~700 M€ d'EV au multiple d'entrée.
B29: Sensibilité du TRI CD&R — multiple de sortie × conversion cash
B30: TRI | C30: Conversion 35% | D30: Conversion 45% | E30: Conversion 60%
B31: Sortie 10.0x | C31: =((($C$15*10-MAX($C$8-(SUM('P&L Carve-out'!$D$18:$H$18)*0.35-5*Hypothèses!$C$34*$C$8),0))*Hypothèses!$C$10)/$C$10)^(1/4.7)-1 -> -0.026513353 | D31: =((($C$15*10-MAX($C$8-(SUM('P&L Carve-out'!$D$18:$H$18)*0.45-5*Hypothèses!$C$34*$C$8),0))*Hypothèses!$C$10)/$C$10)^(1/4.7)-1 -> -0.014514747 | E31: =((($C$15*10-MAX($C$8-(SUM('P&L Carve-out'!$D$18:$H$18)*0.6-5*Hypothèses!$C$34*$C$8),0))*Hypothèses!$C$10)/$C$10)^(1/4.7)-1 -> 0.0025283608
B32: Sortie 12.0x | C32: =((($C$15*12-MAX($C$8-(SUM('P&L Carve-out'!$D$18:$H$18)*0.35-5*Hypothèses!$C$34*$C$8),0))*Hypothèses!$C$10)/$C$10)^(1/4.7)-1 -> 0.024045524 | D32: =((($C$15*12-MAX($C$8-(SUM('P&L Carve-out'!$D$18:$H$18)*0.45-5*Hypothèses!$C$34*$C$8),0))*Hypothèses!$C$10)/$C$10)^(1/4.7)-1 -> 0.034041595 | E32: =((($C$15*12-MAX($C$8-(SUM('P&L Carve-out'!$D$18:$H$18)*0.6-5*Hypothèses!$C$34*$C$8),0))*Hypothèses!$C$10)/$C$10)^(1/4.7)-1 -> 0.048396567
B33: Sortie 14.0x | C33: =((($C$15*14-MAX($C$8-(SUM('P&L Carve-out'!$D$18:$H$18)*0.35-5*Hypothèses!$C$34*$C$8),0))*Hypothèses!$C$10)/$C$10)^(1/4.7)-1 -> 0.066764583 | D33: =((($C$15*14-MAX($C$8-(SUM('P&L Carve-out'!$D$18:$H$18)*0.45-5*Hypothèses!$C$34*$C$8),0))*Hypothèses!$C$10)/$C$10)^(1/4.7)-1 -> 0.07538457 | E33: =((($C$15*14-MAX($C$8-(SUM('P&L Carve-out'!$D$18:$H$18)*0.6-5*Hypothèses!$C$34*$C$8),0))*Hypothèses!$C$10)/$C$10)^(1/4.7)-1 -> 0.087853904
B35: Autres sensibilités à tester en phase 2 : coûts stand-alone ±50 M€, sortie TSA 12-30 mois, one-offs 100-250 M€, croissance 1-5 %, levier 3-5x (audit §7.7).
